tests/TestUtils.py
tests/__init__.py
utils/__init__.py
utils/bbox.py
utils/exceptions.py
utils/thresholds.py
text_detector-0.0.3.dist-info/LICENSE
text_detector-0.0.3.dist-info/METADATA
text_detector-0.0.3.dist-info/WHEEL
text_detector-0.0.3.dist-info/top_level.txt
text_detector-0.0.3.dist-info/RECORD
