Metadata-Version: 2.1
Name: text-detector
Version: 0.0.3
Summary: Locating texts in images using computer vision
Home-page: https://github.com/muthuspark/text-detector
Author: Muthu krishnan
Author-email: muthukrishnan749@gmail.com
License: UNKNOWN
Platform: UNKNOWN
Classifier: Programming Language :: Python :: 3
Classifier: License :: OSI Approved :: MIT License
Classifier: Operating System :: OS Independent
Requires-Python: >=3.6
